simplyprint-duet3d.service
simplyprint_duet3d/__init__.py
simplyprint_duet3d/__main__.py
simplyprint_duet3d/gcode.py
simplyprint_duet3d/network.py
simplyprint_duet3d/ota.py
simplyprint_duet3d/printer.py
simplyprint_duet3d/state.py
simplyprint_duet3d/task.py
simplyprint_duet3d/watchdog.py
simplyprint_duet3d/webcam.py
simplyprint_duet3d/cli/__init__.py
simplyprint_duet3d/cli/autodiscover.py
simplyprint_duet3d/cli/install.py
simplyprint_duet3d/duet/__init__.py
simplyprint_duet3d/duet/api.py
simplyprint_duet3d/duet/model.py
simplyprint_duet3d-1.3.15.dist-info/METADATA
simplyprint_duet3d-1.3.15.dist-info/WHEEL
simplyprint_duet3d-1.3.15.dist-info/entry_points.txt
simplyprint_duet3d-1.3.15.dist-info/licenses/LICENSE
simplyprint_duet3d-1.3.15.dist-info/RECORD
