Metadata-Version: 2.4
Name: simplyprint-duet3d
Version: 1.3.15
Summary: SimplyPrint integration with any Duet3D powered RepRapFirmware printers 
Author-email: SimplyPrint <dev@simplyprint.io>, Tim Schneider <tim@meltingplot.net>
License-File: LICENSE
Requires-Python: >=3.9
Requires-Dist: aiohttp>=3.11.13
Requires-Dist: attrs>=25.1.0
Requires-Dist: imageio[ffmpeg]>=2.37.0
Requires-Dist: psutil>=6.1.1
Requires-Dist: pyee>=12.1.1
Requires-Dist: requests-toolbelt>=1.0.0
Requires-Dist: requests>=2.32.5
Requires-Dist: simplyprint-ws-client==1.0.1rc32
Requires-Dist: strenum>=0.4.15
